<?xml version="1.0" encoding="utf-8"?>
<Elements xmlns="http://schemas.microsoft.com/sharepoint/">
  <CustomAction
    Id="Rjesh_Solutions_ExportSelectedDocs"
    RegistrationType="List"
    RegistrationId="101"
    Location="CommandUI.Ribbon">
    <CommandUIExtension>
      <CommandUIDefinitions>
        <CommandUIDefinition
         Location="Ribbon.Documents.Share.Controls._children">
          <Button
           Id="Rjesh.Solutions.ExportToExcelDocs"
           Alt="Export only selected items to Excel"
           Sequence="11"
           Image32by32="/_layouts/images/Rjesh.Solutions/excelflat.png"
           Command="ExportToExcel"
           LabelText="Export to Excel"
           TemplateAlias="o1"/>
        </CommandUIDefinition>
      </CommandUIDefinitions>
      <CommandUIHandlers>
        <CommandUIHandler
         Command="ExportToExcel"
         CommandAction="javascript:Export();"
         EnabledScript="javascript:exporttoexcelenable();"/>
      </CommandUIHandlers>
    </CommandUIExtension>
  </CustomAction>
  <CustomAction
    Id="Rjesh_Solutions_ExportSelectedItems"
    RegistrationType="List"
    RegistrationId="100"
    Location="CommandUI.Ribbon">
    <CommandUIExtension>
      <CommandUIDefinitions>
        <CommandUIDefinition
         Location="Ribbon.ListItem.Share.Controls._children">
          <Button
           Id="Rjesh.Solutions.ExportToExcelItems"
           Alt="Export only selected items to Excel"
           Sequence="11"
           Image32by32="/_layouts/images/Rjesh.Solutions/excelflat.png"
           Command="ExportToExcel"
           LabelText="Export to Excel"
           TemplateAlias="o1"/>
        </CommandUIDefinition>
      </CommandUIDefinitions>
      <CommandUIHandlers>
        <CommandUIHandler
         Command="ExportToExcel"
         CommandAction="javascript:Export();"
         EnabledScript="javascript:exporttoexcelenable();"/>
      </CommandUIHandlers>
    </CommandUIExtension>
  </CustomAction>
  <CustomAction
  Id="Rjesh_Solutions_ExportSelectedItems"
  RegistrationType="List"
  RegistrationId="103"
  Location="CommandUI.Ribbon">
    <CommandUIExtension>
      <CommandUIDefinitions>
        <CommandUIDefinition
         Location="Ribbon.ListItem.Share.Controls._children">
          <Button
           Id="Rjesh.Solutions.ExportToExcelItems"
           Alt="Export only selected items to Excel"
           Sequence="11"
           Image32by32="/_layouts/images/Rjesh.Solutions/excelflat.png"
           Command="ExportToExcel"
           LabelText="Export to Excel"
           TemplateAlias="o1"/>
        </CommandUIDefinition>
      </CommandUIDefinitions>
      <CommandUIHandlers>
        <CommandUIHandler
         Command="ExportToExcel"
         CommandAction="javascript:Export();"
         EnabledScript="javascript:exporttoexcelenable();"/>
      </CommandUIHandlers>
    </CommandUIExtension>
  </CustomAction>
  <CustomAction
  Id="Rjesh_Solutions_ExportSelectedItems"
  RegistrationType="List"
  RegistrationId="104"
  Location="CommandUI.Ribbon">
    <CommandUIExtension>
      <CommandUIDefinitions>
        <CommandUIDefinition
         Location="Ribbon.ListItem.Share.Controls._children">
          <Button
           Id="Rjesh.Solutions.ExportToExcelItems"
           Alt="Export only selected items to Excel"
           Sequence="11"
           Image32by32="/_layouts/images/Rjesh.Solutions/excelflat.png"
           Command="ExportToExcel"
           LabelText="Export to Excel"
           TemplateAlias="o1"/>
        </CommandUIDefinition>
      </CommandUIDefinitions>
      <CommandUIHandlers>
        <CommandUIHandler
         Command="ExportToExcel"
         CommandAction="javascript:Export();"
         EnabledScript="javascript:exporttoexcelenable();"/>
      </CommandUIHandlers>
    </CommandUIExtension>
  </CustomAction>
  <CustomAction
  Id="Rjesh_Solutions_ExportSelectedItems"
  RegistrationType="List"
  RegistrationId="105"
  Location="CommandUI.Ribbon">
    <CommandUIExtension>
      <CommandUIDefinitions>
        <CommandUIDefinition
         Location="Ribbon.ListItem.Share.Controls._children">
          <Button
           Id="Rjesh.Solutions.ExportToExcelItems"
           Alt="Export only selected items to Excel"
           Sequence="11"
           Image32by32="/_layouts/images/Rjesh.Solutions/excelflat.png"
           Command="ExportToExcel"
           LabelText="Export to Excel"
           TemplateAlias="o1"/>
        </CommandUIDefinition>
      </CommandUIDefinitions>
      <CommandUIHandlers>
        <CommandUIHandler
         Command="ExportToExcel"
         CommandAction="javascript:Export();"
         EnabledScript="javascript:exporttoexcelenable();"/>
      </CommandUIHandlers>
    </CommandUIExtension>
  </CustomAction>
  <CustomAction
  Id="Rjesh_Solutions_ExportSelectedItems"
  RegistrationType="List"
  RegistrationId="106"
  Location="CommandUI.Ribbon">
    <CommandUIExtension>
      <CommandUIDefinitions>
        <CommandUIDefinition
         Location="Ribbon.ListItem.Share.Controls._children">
          <Button
           Id="Rjesh.Solutions.ExportToExcelItems"
           Alt="Export only selected items to Excel"
           Sequence="11"
           Image32by32="/_layouts/images/Rjesh.Solutions/excelflat.png"
           Command="ExportToExcel"
           LabelText="Export to Excel"
           TemplateAlias="o1"/>
        </CommandUIDefinition>
      </CommandUIDefinitions>
      <CommandUIHandlers>
        <CommandUIHandler
         Command="ExportToExcel"
         CommandAction="javascript:Export();"
         EnabledScript="javascript:exporttoexcelenable();"/>
      </CommandUIHandlers>
    </CommandUIExtension>
  </CustomAction>
  <CustomAction
  Id="Rjesh_Solutions_ExportSelectedItems"
  RegistrationType="List"
  RegistrationId="107"
  Location="CommandUI.Ribbon">
    <CommandUIExtension>
      <CommandUIDefinitions>
        <CommandUIDefinition
         Location="Ribbon.ListItem.Share.Controls._children">
          <Button
           Id="Rjesh.Solutions.ExportToExcelItems"
           Alt="Export only selected items to Excel"
           Sequence="11"
           Image32by32="/_layouts/images/Rjesh.Solutions/excelflat.png"
           Command="ExportToExcel"
           LabelText="Export to Excel"
           TemplateAlias="o1"/>
        </CommandUIDefinition>
      </CommandUIDefinitions>
      <CommandUIHandlers>
        <CommandUIHandler
         Command="ExportToExcel"
         CommandAction="javascript:Export();"
         EnabledScript="javascript:exporttoexcelenable();"/>
      </CommandUIHandlers>
    </CommandUIExtension>
  </CustomAction>
  <CustomAction
  Id="Rjesh_Solutions_ExportSelectedItems"
  RegistrationType="List"
  RegistrationId="108"
  Location="CommandUI.Ribbon">
    <CommandUIExtension>
      <CommandUIDefinitions>
        <CommandUIDefinition
         Location="Ribbon.ListItem.Share.Controls._children">
          <Button
           Id="Rjesh.Solutions.ExportToExcelItems"
           Alt="Export only selected items to Excel"
           Sequence="11"
           Image32by32="/_layouts/images/Rjesh.Solutions/excelflat.png"
           Command="ExportToExcel"
           LabelText="Export to Excel"
           TemplateAlias="o1"/>
        </CommandUIDefinition>
      </CommandUIDefinitions>
      <CommandUIHandlers>
        <CommandUIHandler
         Command="ExportToExcel"
         CommandAction="javascript:Export();"
         EnabledScript="javascript:exporttoexcelenable();"/>
      </CommandUIHandlers>
    </CommandUIExtension>
  </CustomAction>
  <CustomAction
  Id="Rjesh_Solutions_ExportSelectedItems"
  RegistrationType="List"
  RegistrationId="115"
  Location="CommandUI.Ribbon">
    <CommandUIExtension>
      <CommandUIDefinitions>
        <CommandUIDefinition
         Location="Ribbon.Documents.Share.Controls._children">
          <Button
           Id="Rjesh.Solutions.ExportToExcelItems"
           Alt="Export only selected items to Excel"
           Sequence="11"
           Image32by32="/_layouts/images/Rjesh.Solutions/excelflat.png"
           Command="ExportToExcel"
           LabelText="Export to Excel"
           TemplateAlias="o1"/>
        </CommandUIDefinition>
      </CommandUIDefinitions>
      <CommandUIHandlers>
        <CommandUIHandler
         Command="ExportToExcel"
         CommandAction="javascript:Export();"
         EnabledScript="javascript:exporttoexcelenable();"/>
      </CommandUIHandlers>
    </CommandUIExtension>
  </CustomAction>
  <CustomAction
  Id="Rjesh_Solutions_ExportSelectedItems"
  RegistrationType="List"
  RegistrationId="119"
  Location="CommandUI.Ribbon">
    <CommandUIExtension>
      <CommandUIDefinitions>
        <CommandUIDefinition
         Location="Ribbon.Documents.Share.Controls._children">
          <Button
           Id="Rjesh.Solutions.ExportToExcelItems"
           Alt="Export only selected items to Excel"
           Sequence="11"
           Image32by32="/_layouts/images/Rjesh.Solutions/excelflat.png"
           Command="ExportToExcel"
           LabelText="Export to Excel"
           TemplateAlias="o1"/>
        </CommandUIDefinition>
      </CommandUIDefinitions>
      <CommandUIHandlers>
        <CommandUIHandler
         Command="ExportToExcel"
         CommandAction="javascript:Export();"
         EnabledScript="javascript:exporttoexcelenable();"/>
      </CommandUIHandlers>
    </CommandUIExtension>
  </CustomAction>
  <CustomAction Id="Ribbon.Library.Actions.Scripts"
                Location="ScriptLink"
                ScriptSrc="/_Layouts/Rjesh.Solutions/Exporttoexcel_min.js" />
</Elements>